stock_notifier/__init__.py
stock_notifier/command_line.py
stock_notifier/stock.py
stock_notifier/stock_notifier.py
stock_notifier/stock_config/__init__.py
stock_notifier/stock_config/nasdaq_stock_config.py
stock_notifier/stock_config/stock_config.py
stock_notifier-0.0.2.dist-info/LICENSE
stock_notifier-0.0.2.dist-info/METADATA
stock_notifier-0.0.2.dist-info/WHEEL
stock_notifier-0.0.2.dist-info/entry_points.txt
stock_notifier-0.0.2.dist-info/top_level.txt
stock_notifier-0.0.2.dist-info/RECORD
