Metadata-Version: 2.1
Name: stock-notifier
Version: 0.0.2
Summary: An application that provides system notifications for changes in stock values
Home-page: https://github.com/saswatraj/stock_notifier
Author: Saswat Raj
Author-email: saswatraj@outlook.com
License: UNKNOWN
Platform: UNKNOWN
Classifier: Programming Language :: Python :: 2.7
Classifier: License :: OSI Approved :: MIT License
Classifier: Environment :: MacOS X
Requires-Dist: pync
Requires-Dist: BeautifulSoup
